README.md
setup.cfg
setup.py
sumolib/__init__.py
sumolib/color.py
sumolib/geomhelper.py
sumolib/miscutils.py
sumolib/options.py
sumolib/route.py
sumolib/xml.py
sumolib/files/__init__.py
sumolib/files/additional.py
sumolib/files/selection.py
sumolib/net/__init__.py
sumolib/net/connection.py
sumolib/net/edge.py
sumolib/net/lane.py
sumolib/net/node.py
sumolib/net/roundabout.py
sumolib/net/generator/__init__.py
sumolib/net/generator/corridor.py
sumolib/net/generator/cross.py
sumolib/net/generator/demand.py
sumolib/net/generator/grid.py
sumolib/net/generator/network.py
sumolib/net/generator/straight.py
sumolib/output/__init__.py
sumolib/output/dump.py
sumolib/output/inductionloop.py
sumolib/output/convert/__init__.py
sumolib/output/convert/fcdfilter.py
sumolib/output/convert/gpsdat.py
sumolib/output/convert/gpx.py
sumolib/output/convert/ns2.py
sumolib/output/convert/omnet.py
sumolib/output/convert/phem.py
sumolib/output/convert/poi.py
sumolib/output/convert/shawn.py
sumolib/scenario/__init__.py
sumolib/scenario/checkFlows.py
sumolib/scenario/pop2.py
sumolib/scenario/runsdb.py
sumolib/scenario/scenarios/__init__.py
sumolib/scenario/scenarios/basic_corridor.py
sumolib/scenario/scenarios/basic_cross.py
sumolib/scenario/scenarios/basic_crossl.py
sumolib/scenario/scenarios/basic_net.py
sumolib/scenario/scenarios/basic_rilsacorridor3.py
sumolib/scenario/scenarios/basic_rilsanet.py
sumolib/scenario/scenarios/basic_rilsanet2x2.py
sumolib/scenario/scenarios/real_world.py
sumolib/scenario/scenarios/rilsa1.py
sumolib/scenario/scenarios/rilsa1_both_tls.py
sumolib/scenario/scenarios/rilsa1_both_tls24.py
sumolib/scenario/scenarios/rilsa1_out_tls.py
sumolib/scenario/scenarios/rilsa1_out_tls24.py
sumolib/sensors/__init__.py
sumolib/sensors/inductive_loop.py
sumolib/shapes/__init__.py
sumolib/shapes/poi.py
sumolib/shapes/polygon.py
sumolib/visualization/__init__.py
sumolib/visualization/helpers.py
sumotools.egg-info/PKG-INFO
sumotools.egg-info/SOURCES.txt
sumotools.egg-info/dependency_links.txt
sumotools.egg-info/top_level.txt
traci/__init__.py
traci/_edge.py
traci/_gui.py
traci/_inductionloop.py
traci/_junction.py
