Metadata-Version: 1.2
Name: sumotools
Version: 0.7.2
Summary: Redistribution of the SUMO tools modules for use in the TrafficSenseMSD project
Home-page: https://github.com/TrafficSenseMSD/SumoTools
Author: TrafficSenseMSD
License: UNKNOWN
Keywords: sumo,traffic,simulation
Platform: UNKNOWN
Requires-Python: >=3.5
